{
  "_note1": "KEEP THIS FILE! Check it into a version control system (VCS) like git.",
  "_note2": "ObjectBox manages crucial IDs for your object model. See docs for details.",
  "_note3": "If you have VCS merge conflicts, you must resolve them according to ObjectBox docs.",
  "entities": [
    {
      "id": "1:5327643524230729498",
      "lastPropertyId": "8:8911073921537597230",
      "name": "Task",
      "properties": [
        {
          "id": "1:4674537023312550545",
          "name": "id",
          "type": 6,
          "flags": 1
        },
        {
          "id": "2:7487719864805207530",
          "name": "title",
          "type": 9
        },
        {
          "id": "3:2811964540761023302",
          "name": "description",
          "type": 9
        },
        {
          "id": "4:703498212147014801",
          "name": "isDone",
          "type": 1
        },
        {
          "id": "5:3031948797769794654",
          "name": "isArchived",
          "type": 1
        },
        {
          "id": "6:5136866058053075914",
          "name": "createdAt",
          "type": 10
        },
        {
          "id": "7:4383474965537481400",
          "name": "finishedAt",
          "type": 10
        },
        {
          "id": "8:8911073921537597230",
          "name": "doAt",
          "type": 10
        }
      ],
      "relations": [
        {
          "id": "1:5506896385409575212",
          "name": "subtasks",
          "targetId": "2:974781339298099500"
        }
      ]
    },
    {
      "id": "2:974781339298099500",
      "lastPropertyId": "3:8890510066313504040",
      "name": "SubTask",
      "properties": [
        {
          "id": "1:6703443556723780945",
          "name": "id",
          "type": 6,
          "flags": 1
        },
        {
          "id": "2:5213720774170321556",
          "name": "title",
          "type": 9
        },
        {
          "id": "3:8890510066313504040",
          "name": "isDone",
          "type": 1
        }
      ],
      "relations": []
    }
  ],
  "lastEntityId": "2:974781339298099500",
  "lastIndexId": "0:0",
  "lastRelationId": "1:5506896385409575212",
  "lastSequenceId": "0:0",
  "modelVersion": 5,
  "modelVersionParserMinimum": 5,
  "retiredEntityUids": [],
  "retiredIndexUids": [],
  "retiredPropertyUids": [],
  "retiredRelationUids": [],
  "version": 1
}